ssb_hermes/__init__.py
ssb_hermes/__main__.py
ssb_hermes/_find_match_rules.py
ssb_hermes/_functions.py
ssb_hermes/example_data/test_data.csv
ssb_hermes/example_data/test_registry.csv
ssb_hermes/functions.py
ssb_hermes/py.typed
ssb_hermes-0.0.5.dist-info/LICENSE
ssb_hermes-0.0.5.dist-info/METADATA
ssb_hermes-0.0.5.dist-info/WHEEL
ssb_hermes-0.0.5.dist-info/entry_points.txt
ssb_hermes-0.0.5.dist-info/RECORD
