Metadata-Version: 2.1
Name: ssb-hermes
Version: 0.0.5
Summary: SSB Hermes
Home-page: https://github.com/statisticsnorway/ssb-hermes
License: GPL-3.0
Author: Edvard Garmannslund
Author-email: ged@ssb.no
Requires-Python: >=3.9,<4.0
Classifier: Development Status :: 3 - Alpha
Classifier: License :: OSI Approved :: GNU General Public License v3 (GPLv3)
Classifier: Programming Language :: Python :: 3
Classifier: Programming Language :: Python :: 3.9
Classifier: Programming Language :: Python :: 3.10
Classifier: Programming Language :: Python :: 3.11
Classifier: Programming Language :: Python :: 3.12
Requires-Dist: click (>=8.0.1)
Requires-Dist: fuzzywuzzy (>=0.18.0,<0.19.0)
Requires-Dist: numpy (>=1.26.2,<2.0.0)
Requires-Dist: pandas (>=2.1.4,<3.0.0)
Requires-Dist: python-levenshtein (>=0.23.0,<0.24.0)
Project-URL: Changelog, https://github.com/statisticsnorway/ssb-hermes/releases
Project-URL: Documentation, https://statisticsnorway.github.io/ssb-hermes
Project-URL: Repository, https://github.com/statisticsnorway/ssb-hermes
